[{"id": "163837210698", "name": "Richie Stanaway"}, {"id": "713798348667267", "name": "Arjen Robben Fans."}, {"id": "481368871994328", "name": "Hulk - Zenit"}, {"id": "222989457881504", "name": "Bhuvneshwar Kumar"}, {"id": "190575714312562", "name": "Oscar"}, {"id": "104358599601495", "name": "Chris Gayle"}, {"id": "149809868626", "name": "Federer Roger"}, {"id": "640477456018129", "name": "Glenn  Maxwell"}, {"id": "474431685992041", "name": "Virat Kohli - The Run Machine"}, {"id": "326546224099154", "name": "Virat Kohli"}, {"id": "108661895824433", "name": "AB de Villiers"}, {"id": "262322740587514", "name": "Akshay Zine"}, {"id": "16814976965", "name": "Andy Murray"}, {"id": "344128252278047", "name": "Sachin Tendulkar"}, {"id": "258438354179375", "name": "Kevin Pietersen"}, {"id": "20242388857", "name": "Usain Bolt"}, {"id": "440975945912772", "name": "I Love Dhoni Helicopter Shot"}, {"id": "118306468218564", "name": "Circle of Cricket India"}, {"id": "100787839962234", "name": "Saina Nehwal"}, {"id": "108122792548976", "name": "Yuvraj Singh"}, {"id": "130561483625985", "name": "Virender Sehwag"}]